zeuslab/__init__.py
zeuslab/hercules/__init__.py
zeuslab/hercules/core.py
zeuslab/hercules/tools/__init__.py
zeuslab-1.2.1.dist-info/METADATA
zeuslab-1.2.1.dist-info/WHEEL
zeuslab-1.2.1.dist-info/top_level.txt
zeuslab-1.2.1.dist-info/RECORD
