Metadata-Version: 2.1
Name: zeuslab
Version: 1.2.1
Summary: ZeusLab core package — building blocks for agentic AI and intelligent systems.
Home-page: https://github.com/zeuslabs-ai/hercules
Author: Zeus Lab - Gokulakrishnan
Author-email: gokulskrishnan74@gmail.com
License: UNKNOWN
Platform: UNKNOWN
Classifier: Programming Language :: Python :: 3
Classifier: License :: OSI Approved :: MIT License
Classifier: Operating System :: OS Independent
Classifier: Development Status :: 3 - Alpha
Classifier: Intended Audience :: Developers
Classifier: Topic :: Software Development :: Libraries :: Python Modules
Requires-Python: >=3.7
Requires-Dist: autogen
Requires-Dist: requests
